biblio/__init__.py
biblio/biblio.py
ugentbiblio-0.2.2.dist-info/DESCRIPTION.rst
ugentbiblio-0.2.2.dist-info/METADATA
ugentbiblio-0.2.2.dist-info/RECORD
ugentbiblio-0.2.2.dist-info/WHEEL
ugentbiblio-0.2.2.dist-info/metadata.json
ugentbiblio-0.2.2.dist-info/top_level.txt
