Metadata-Version: 2.0
Name: ugentbiblio
Version: 0.2.2
Summary: Connector to the API of Ghent University Academic Bibliography
Home-page: https://github.com/megasnort/python-ugent-biblio
Author: Stef Bastiaansen
Author-email: stef.bastiaansen@ugent.be
License: Apache
Keywords: ugent biblio library publications
Platform: UNKNOWN
Classifier: Development Status :: 4 - Beta
Classifier: Programming Language :: Python
Classifier: Intended Audience :: Developers
Classifier: Intended Audience :: Education
Classifier: Intended Audience :: Science/Research
Classifier: License :: OSI Approved :: Apache Software License
Requires-Dist: requests
